tigas/__init__.py
tigas/api.py
tigas/model_hub.py
tigas/data/__init__.py
tigas/data/dataset.py
tigas/data/loaders.py
tigas/data/transforms.py
tigas/metrics/__init__.py
tigas/metrics/components.py
tigas/metrics/tigas_metric.py
tigas/models/__init__.py
tigas/models/attention.py
tigas/models/constants.py
tigas/models/feature_extractors.py
tigas/models/layers.py
tigas/models/tigas_model.py
tigas/training/__init__.py
tigas/training/losses.py
tigas/training/optimizers.py
tigas/training/trainer.py
tigas/utils/__init__.py
tigas/utils/config.py
tigas/utils/input_processor.py
tigas/utils/visualization.py
tigas_metric-0.1.1.dist-info/licenses/LICENSE
tigas_metric-0.1.1.dist-info/METADATA
tigas_metric-0.1.1.dist-info/WHEEL
tigas_metric-0.1.1.dist-info/top_level.txt
tigas_metric-0.1.1.dist-info/RECORD
