Metadata-Version: 2.4
Name: tigas-metric
Version: 0.1.1
Summary: Trained Image Generation Authenticity Score - A neural metric for assessing image realism
Home-page: https://github.com/H1merka/TIGAS
Author: TIGAS Project Team
Author-email: TIGAS Project Team <morgenstern.dmitrij.701@gmail.com>
License-Expression: MIT
Project-URL: Homepage, https://github.com/H1merka/TIGAS
Project-URL: Repository, https://github.com/H1merka/TIGAS
Project-URL: Documentation, https://github.com/H1merka/TIGAS#readme
Keywords: deep learning,computer vision,image quality,generative models,gan evaluation,pytorch
Classifier: Development Status :: 3 - Alpha
Classifier: Intended Audience :: Science/Research
Classifier: Topic :: Scientific/Engineering :: Artificial Intelligence
Classifier: Programming Language :: Python :: 3
Classifier: Programming Language :: Python :: 3.8
Classifier: Programming Language :: Python :: 3.9
Classifier: Programming Language :: Python :: 3.10
Classifier: Programming Language :: Python :: 3.11
Requires-Python: >=3.8
License-File: LICENSE
Requires-Dist: torch>=2.2.0
Requires-Dist: torchvision>=0.17.0
Requires-Dist: numpy>=1.24.0
Requires-Dist: scipy>=1.10.0
Requires-Dist: scikit-learn>=1.3.0
Requires-Dist: pillow>=10.0.0
Requires-Dist: opencv-python>=4.8.0
Requires-Dist: pandas>=2.0.0
Requires-Dist: huggingface-hub>=0.19.0
Requires-Dist: matplotlib>=3.5.0
Requires-Dist: seaborn>=0.11.0
Requires-Dist: tqdm>=4.60.0
Provides-Extra: dev
Requires-Dist: pytest>=7.0.0; extra == "dev"
Requires-Dist: pytest-cov>=3.0.0; extra == "dev"
Requires-Dist: black>=22.0.0; extra == "dev"
Requires-Dist: flake8>=4.0.0; extra == "dev"
Requires-Dist: isort>=5.10.0; extra == "dev"
Requires-Dist: mypy>=0.950; extra == "dev"
Requires-Dist: twine>=4.0.0; extra == "dev"
Requires-Dist: build>=0.7.0; extra == "dev"
Provides-Extra: training
Requires-Dist: tensorboard>=2.9.0; extra == "training"
Requires-Dist: wandb>=0.12.0; extra == "training"
Dynamic: author
Dynamic: home-page
Dynamic: license-file
Dynamic: requires-python
